{
    "language": "Ro",
    "header": {
        "address": "strada Păcii 10",
        "cartbutton": "Coșul meu"
    },
    "searchbar": {
        "placeholder" :"Caută restaurante"
    },
    "addbutton": "Adaugă",
    "emptycart": {
        "button": "Coș gol",
        "modal": {
            "title": "Coșul tău este gol!",
            "additems": "Adaugă produse în coș pentru a continua cumpărăturile."
        }
    },
    "restaurant": {
        "delivery": "Prețul livrării:&nbsp;",
        "payment": {
            "card": "Card",
            "cash": "Cash"
        },
        "map": "Vizualizați pe hartă",
        "description": "Restaurantele McDonald's oferă produse 100% proaspete şi de calitate în orice loc şi în orice moment"
    },
    "cart": {
        "edit": "Editează",
        "delete": "Șterge",
        "delivery": "Livrare:",
        "total": "Total: ",
        "button_next": "Continuă"
    },
  
        "help": {
            "title": "Ajutor",
            "delivery": "Livrare"
        },
        "ifood": {
            "about": "Despre noi",
            "become_courier": "Devino curier",
            "become_partner": "Devino partener",
            "mastercard_promo": "Promo MasterCard"
        },
        "legal": {
            "title": "Juridic",
            "terms": "Termeni și condiții",
            "confidentiality": "Politica de confidențialitate",
            "cookies": "Politica cookies"
        },
        "support": {
            "title": "Suport",
            "phone": "Telefon:&nbsp;(022) 000 100",
            "email": "Email:&nbsp;support@ifood.md"
        },
        "subscribe": "Abonează-te",
        "rights_reserved": "Toate drepturile sunt rezervate.",


        "schedule": {
            "monday": "Luni:&nbsp",
            "tuesday": "Marți:&nbsp",
            "wednesday": "Miercuri:&nbsp",
            "thursday": "Joi:&nbsp",
            "friday": "Vineri:&nbsp",
            "saturday": "Sâmbătă:&nbsp",
            "sunday": "Duminică:&nbsp"
        },
        "promo": {
            "title": "livrare gratuită",
            "description": "Achită cu Mastercard de la 200 lei și primește livrare gratuită"
        }



}